[{"af":4,"avg":194.6214933333,"dst_addr":"104.75.200.9","dst_name":"www.fifa.com","dup":0,"from":"41.186.44.106","fw":4960,"group_id":20255290,"lts":25,"max":205.106085,"min":187.993485,"msm_id":20255290,"msm_name":"Ping","prb_id":21607,"proto":"ICMP","rcvd":3,"result":[{"rtt":187.993485},{"rtt":190.76491},{"rtt":205.106085}],"sent":3,"size":48,"src_addr":"192.168.1.59","step":null,"stored_timestamp":1552888757,"timestamp":1552888749,"ttl":57,"ttr":198.08418,"type":"ping"},{"af":4,"avg":76.6985993333,"dst_addr":"104.75.200.9","dst_name":"www.fifa.com","dup":0,"from":"196.49.7.52","fw":4950,"group_id":20255290,"lts":71,"max":80.359484,"min":74.504771,"msm_id":20255290,"msm_name":"Ping","prb_id":6361,"proto":"ICMP","rcvd":3,"result":[{"rtt":75.231543},{"rtt":74.504771},{"rtt":80.359484}],"sent":3,"size":48,"src_addr":"196.49.7.52","step":null,"stored_timestamp":1552888762,"timestamp":1552888748,"ttl":53,"ttr":171.253799,"type":"ping"}]